pycloudflared/__init__.py
pycloudflared/__main__.py
pycloudflared/__version__.py
pycloudflared/download_url.toml
pycloudflared/try_cloudflare.py
pycloudflared/util.py
pycloudflared-0.2.0.dist-info/entry_points.txt
pycloudflared-0.2.0.dist-info/WHEEL
pycloudflared-0.2.0.dist-info/METADATA
pycloudflared-0.2.0.dist-info/licenses/LICENSE.md
pycloudflared-0.2.0.dist-info/RECORD
