Metadata-Version: 2.1
Name: pycloudflared
Version: 0.2.0
Summary: unofficial cloudflared python wrapper
License: MIT
Author-email: dowon <ks2515@naver.com>
Requires-Python: >=3.7
Project-URL: repository, https://github.com/Bing-su/pycloudflared
